py1090/__init__.py
py1090/collection.py
py1090/connection.py
py1090/helpers.py
py1090/message.py
py1090-1.1.dist-info/LICENSE.txt
py1090-1.1.dist-info/METADATA
py1090-1.1.dist-info/WHEEL
py1090-1.1.dist-info/top_level.txt
py1090-1.1.dist-info/RECORD
